apibtc/__init__.py
apibtc/agent.py
apibtc/enumsandcodes.py
apibtc/frames_pb2.py
apibtc/schnorr_lib.py
apibtc/wallet.py
apibtc/walletstreaming.py
apibtc-1.0.16.dist-info/LICENSE
apibtc-1.0.16.dist-info/METADATA
apibtc-1.0.16.dist-info/WHEEL
apibtc-1.0.16.dist-info/top_level.txt
apibtc-1.0.16.dist-info/RECORD
