Metadata-Version: 2.1
Name: apibtc
Version: 1.0.16
Summary: Python client for interacting with the Hyperlabs Bitcoin API
Author-email: thehyperlabs <info@thehyperlabs.com>
License:                                  Apache License
Project-URL: Homepage, https://apibtc.org/
Project-URL: Repository, https://github.com/DontTrustVerifyOrg/apibtc.git
Requires-Python: >=3.8
License-File: LICENSE
Requires-Dist: requests>=2.31.0
Requires-Dist: protobuf>=4.25.2
Requires-Dist: bip32utils
Requires-Dist: mnemonic
Requires-Dist: pandas>=2.2.0
Requires-Dist: signalrcore>=0.9.5
Requires-Dist: prompt_toolkit>=3.0.43
Requires-Dist: termcolor>=2.4.0
Requires-Dist: openai>=1.17.0
Requires-Dist: rich>=13.7.1
